freeze_uuid/__init__.py
freeze_uuid/main.py
tests/__init__.py
tests/test_api.py
tests/testdata.py
freeze_uuid-0.4.3.dist-info/LICENSE
freeze_uuid-0.4.3.dist-info/METADATA
freeze_uuid-0.4.3.dist-info/WHEEL
freeze_uuid-0.4.3.dist-info/top_level.txt
freeze_uuid-0.4.3.dist-info/RECORD
