Metadata-Version: 2.1
Name: freeze-uuid
Version: 0.4.3
Summary: Python package for mocking uuid.
Home-page: https://github.com/alaex777/freeze-uuid
Author: Alexander Balashov
Author-email: alaex777@gmail.com
Classifier: Programming Language :: Python :: 3
Classifier: License :: OSI Approved :: MIT License
Classifier: Operating System :: OS Independent
Requires-Python: >=3.9
License-File: LICENSE
